psub/__init__.py
psub/cli.py
psub/main.py
psub/submission_scripts.py
psub/utilities/__init__.py
psub/utilities/check_cpu_on_interactive.py
psub/utilities/sge_check_cpu_util.py
psub/utilities/sge_monitor.py
psub/utilities/sge_monitor_tui2.py
psub/utilities/sge_monitor_tui_scrollview.py
tests/__init__.py
tests/test_psub.py
psub-0.1.2a0.dist-info/METADATA
psub-0.1.2a0.dist-info/WHEEL
psub-0.1.2a0.dist-info/entry_points.txt
psub-0.1.2a0.dist-info/top_level.txt
psub-0.1.2a0.dist-info/RECORD
