Metadata-Version: 2.1
Name: psub
Version: 0.1.2a0
Summary: Submit and monitor array jobs on the Hoffman2 cluster with minimal configuration.
Home-page: https://github.com/udincer/psub
Author: Tev Dincer
Author-email: umutdincer@gmail.com
License: UNKNOWN
Platform: UNKNOWN
Classifier: Programming Language :: Python :: 3
Classifier: Operating System :: OS Independent
Requires-Python: >=3.7
Requires-Dist: simple-term-menu
